[
	{"filename":"Turret_turret_fire_4x_01","caption":"[Turret fire]"},
	{"filename":"Turret_turret_fire_4x_02","caption":"[Turret fire]"},
	{"filename":"Turret_turret_fire_4x_03","caption":"[Turret fire]"},
	{"filename":"Turret_turretlaunched01","caption":"Whee!"},
	{"filename":"Turret_turretlaunched04","caption":"Noooooo!"},
	{"filename":"Turret_turretlaunched08","caption":"Hooray!"},
	{"filename":"Turret_turretlaunched11","caption":"Goodbye!"},
	{"filename":"Turret_turretlaunched02","caption":"Wheeeeeeee!"},
	{"filename":"Turret_turretlaunched03","caption":"I'm afraid of heights!"},
	{"filename":"Turret_turretlaunched05","caption":"See you soon!"},
	{"filename":"Turret_turretlaunched06","caption":"I'm scared!"},
	{"filename":"Turret_turretlaunched07","caption":"I'm scared!"},
	{"filename":"Turret_turretlaunched09","caption":"Glorious freedom!"},
	{"filename":"Turret_turretlaunched10","caption":"I'm flyinnnng!"},
	{"filename":"Turret_turretlightbridgeblock01","caption":"Come closer."},
	{"filename":"Turret_turretlightbridgeblock02","caption":"Something's wrong..."},
	{"filename":"Turret_turretlightbridgeblock03","caption":"What are you doing?"},
	{"filename":"Turret_turretlightbridgeblock04","caption":"Failure..."},
	{"filename":"Turret_turretshotbylaser01","caption":"Ow!"},
	{"filename":"Turret_turretshotbylaser02","caption":"Owww!"},
	{"filename":"Turret_turretshotbylaser03","caption":"Owwwww!"},
	{"filename":"Turret_turretshotbylaser04","caption":"It burns."},
	{"filename":"Turret_turretshotbylaser05","caption":"I'm on fire."},
	{"filename":"Turret_turretshotbylaser06","caption":"I'm on fire ow."},
	{"filename":"Turret_turretshotbylaser07","caption":"Please stop."},
	{"filename":"Turret_turretshotbylaser08","caption":"You've made your point."},
	{"filename":"Turret_turretshotbylaser09","caption":"Okay, you win."},
	{"filename":"Turret_turretshotbylaser10","caption":"This is not good."},
	{"filename":"Turret_turretsquashed01","caption":"Arrrrgh!"},
	{"filename":"Turret_turretsquashed02","caption":"Owwww!"},
	{"filename":"Turret_turretsquashed03","caption":"Can't breathe..."},
	{"filename":"Turret_turretsquashed04","caption":"Excuse me, you're squishing me."},
	{"filename":"Turret_turretsquashed05","caption":"Um, hello?"},
	{"filename":"Turret_turretsquashed06","caption":"Help! Being squished!"},
	{"filename":"Turret_turretwitnessdeath01","caption":"Good shot!"},
	{"filename":"Turret_turretwitnessdeath02","caption":"Well done!"},
	{"filename":"Turret_turretwitnessdeath03","caption":"I need backup!"},
	{"filename":"Turret_turretwitnessdeath04","caption":"You have excellent aim!"},
	{"filename":"Turret_turretwitnessdeath05","caption":"I never liked her."},
	{"filename":"Turret_turretwitnessdeath06","caption":"These things happen."},
	{"filename":"Turret_turretwitnessdeath07","caption":"That was nobody's fault."},
	{"filename":"Turret_turretwitnessdeath08","caption":"She was provoking you."},
	{"filename":"Turret_turretwitnessdeath09","caption":"Oh dear."},
	{"filename":"Turret_turretwitnessdeath10","caption":"Oh my."},
	{"filename":"Turret_turretwitnessdeath11","caption":"I blame myself."},
	{"filename":"Turret_turretwitnessdeath12","caption":"She probably deserved it."},
	{"filename":"Turret_turretwitnessdeath13","caption":"I saw it. It was an accident."},
	{"filename":"Turret_turretwitnessdeath14","caption":"She's probably OK."},
	{"filename":"Turret_turretwitnessdeath15","caption":"Noted."},
	{"filename":"Turret_sp_sabotage_factory_good_prerange01","caption":"Target acquired."},
	{"filename":"Turret_sp_sabotage_factory_template01","caption":"Hello?"},
	{"filename":"Turret_sp_sabotage_factory_good_pass01","caption":"Hello."},
	{"filename":"Turret_sp_sabotage_factory_good_fail01","caption":"Why?"},
	{"filename":"Turret_sp_sabotage_factory_good_fail02","caption":"I did everything you asked!"},
	{"filename":"Turret_sp_sabotage_factory_good_fail03","caption":"I don't understand!"},
	{"filename":"Turret_sp_sabotage_factory_good_fail04","caption":"I'm fine!"},
	{"filename":"Turret_sp_sabotage_factory_good_fail05","caption":"AHHHHHHHHH!"},
	{"filename":"Turret_sp_sabotage_factory_good_fail06","caption":"Wheeeeee-OH NO!"},
	{"filename":"Turret_sp_sabotage_factory_good_fail07","caption":"Why?"},
	{"filename":"Turret_active","caption":"[Activation sound]"},
	{"filename":"Turret_alarm","caption":"[Alarm sound]"},
	{"filename":"Turret_alert","caption":"[Alert sound]"},
	{"filename":"Turret_deploy","caption":"[Deploy sound]"},
	{"filename":"Turret_die","caption":"[Death sound]"},
	{"filename":"Turret_ping","caption":"[Ping sound]"},
	{"filename":"Turret_retract","caption":"[Retract sound]"},
	{"filename":"Turret_turret_active_1","caption":"Hi?"},
	{"filename":"Turret_turret_active_2","caption":"Target acquired."},
	{"filename":"Turret_turret_active_4","caption":"Firing."},
	{"filename":"Turret_turret_active_5","caption":"Hello? Friend."},
	{"filename":"Turret_turret_active_6","caption":"Gotcha!"},
	{"filename":"Turret_turret_active_7","caption":"There you are."},
	{"filename":"Turret_turret_active_8","caption":"I see you."},
	{"filename":"Turret_turret_active_3","caption":"Dispensing product."},
	{"filename":"Turret_turret_autosearch_1","caption":"Hello!"},
	{"filename":"Turret_turret_autosearch_2","caption":"Searching."},
	{"filename":"Turret_turret_autosearch_4","caption":"Sentry mode activated."},
	{"filename":"Turret_turret_autosearch_5","caption":"Is anyone there?"},
	{"filename":"Turret_turret_autosearch_6","caption":"Could you come over here?"},
	{"filename":"Turret_turret_autosearch_3","caption":"Canvassing."},
	{"filename":"Turret_turret_collide_1","caption":"Coming through!"},
	{"filename":"Turret_turret_collide_2","caption":"Excuse me."},
	{"filename":"Turret_turret_collide_3","caption":"Sorry."},
	{"filename":"Turret_turret_collide_4","caption":"My fault."},
	{"filename":"Turret_turret_collide_5","caption":"Oh!"},
	{"filename":"Turret_turret_deploy_1","caption":"Hello?"},
	{"filename":"Turret_turret_deploy_2","caption":"Deploying."},
	{"filename":"Turret_turret_deploy_3","caption":"Preparing to dispense product."},
	{"filename":"Turret_turret_deploy_4","caption":"Activated."},
	{"filename":"Turret_turret_deploy_5","caption":"There you are."},
	{"filename":"Turret_turret_deploy_6","caption":"Who's there?"},
	{"filename":"Turret_turret_disabled_2","caption":"Critical error."},
	{"filename":"Turret_turret_disabled_4","caption":"Shutting down."},
	{"filename":"Turret_turret_disabled_5","caption":"I don't blame you."},
	{"filename":"Turret_turret_disabled_6","caption":"I don't hate you."},
	{"filename":"Turret_turret_disabled_7","caption":"Why..."},
	{"filename":"Turret_turret_disabled_8","caption":"No hard feelings."},
	{"filename":"Turret_turret_disabled_1","caption":"Ahahaha."},
	{"filename":"Turret_turret_disabled_3","caption":"Sorry, we're closed."},
	{"filename":"Turret_turret_pickup_1","caption":"Hey!"},
	{"filename":"Turret_turret_pickup_3","caption":"Put me down!"},
	{"filename":"Turret_turret_pickup_6","caption":"Who ARE you?"},
	{"filename":"Turret_turret_pickup_7","caption":"Hey."},
	{"filename":"Turret_turret_pickup_8","caption":"Please put me down."},
	{"filename":"Turret_turret_pickup_9","caption":"Help!"},
	{"filename":"Turret_turret_pickup_10","caption":"Uh oh."},
	{"filename":"Turret_turret_pickup_2","caption":"Hey hey hey!"},
	{"filename":"Turret_turret_pickup_4","caption":"Woooaaah!"},
	{"filename":"Turret_turret_pickup_5","caption":"Illegal operation."},
	{"filename":"Turret_turret_retire_1","caption":"Goodbye."},
	{"filename":"Turret_turret_retire_2","caption":"Sleep mode activated."},
	{"filename":"Turret_turret_retire_3","caption":"Your business is appreciated."},
	{"filename":"Turret_turret_retire_4","caption":"Hibernating."},
	{"filename":"Turret_turret_retire_5","caption":"Goodnight."},
	{"filename":"Turret_turret_retire_6","caption":"Resting."},
	{"filename":"Turret_turret_retire_7","caption":"Nap time."},
	{"filename":"Turret_turret_search_1","caption":"Are you still there?"},
	{"filename":"Turret_turret_search_2","caption":"Target lost."},
	{"filename":"Turret_turret_search_4","caption":"Searching."},
	{"filename":"Turret_turret_search_3","caption":"Can I help you?"},
	{"filename":"Turret_turret_fizzler_1","caption":"Ow ow ow!"},
	{"filename":"Turret_turret_shotat_1","caption":"Hey! It's me!"},
	{"filename":"Turret_turret_shotat_2","caption":"Don't shoot!"},
	{"filename":"Turret_turret_shotat_3","caption":"Stop shooting!"},
	{"filename":"Turret_turret_tipped_2","caption":"Self test error."},
	{"filename":"Turret_turret_tipped_4","caption":"Malfunctioning."},
	{"filename":"Turret_turret_tipped_5","caption":"Aaaah."},
	{"filename":"Turret_turret_tipped_6","caption":"Ow ow ow ow owww."},
	{"filename":"Turret_turret_tipped_1","caption":"Aah."},
	{"filename":"Turret_turret_tipped_3","caption":"Unknown error."},
	{"filename":"Turret_turret_suppress_1","caption":"Hold still."},
	{"filename":"Turret_turret_suppress_2","caption":"Target suppressed."},
	{"filename":"Turret_turret_suppress_3","caption":"Free samples."},
	{"filename":"Turret_turret_suppress_4","caption":"Suppressing."},
	{"filename":"Turret_turret_protect_humans01","caption":"But I need to protect the humans!"}
]
